as_doraemon/__init__.py
as_doraemon-1.0.0.dist-info/LICENSE
as_doraemon-1.0.0.dist-info/METADATA
as_doraemon-1.0.0.dist-info/WHEEL
as_doraemon-1.0.0.dist-info/top_level.txt
as_doraemon-1.0.0.dist-info/RECORD
