Metadata-Version: 2.1
Name: as-doraemon
Version: 1.0.0
Summary: A Python package to draw doraemon using turtle
Home-page: https://github.com/shivasai-391/as_doraemon
Author: Alle Shiva Sai
Author-email: lovelynikki391@gmail.com
License: MIT
Platform: UNKNOWN
Classifier: License :: OSI Approved :: MIT License
Classifier: Programming Language :: Python :: 3
Classifier: Programming Language :: Python :: 3.9
